README.md
setup.py
formatter/__init__.py
formatter/exceptions.py
formatter/formatter.py
formatter/parser.py
formatter/source.py
formatter/tree/__init__.py
formatter/tree/nodes.py
formatter/tree/serializer.py
stformatter.egg-info/PKG-INFO
stformatter.egg-info/SOURCES.txt
stformatter.egg-info/dependency_links.txt
stformatter.egg-info/entry_points.txt
stformatter.egg-info/requires.txt
stformatter.egg-info/top_level.txt
tests/__init__.py
tests/conftest.py
tests/parametrize_set.py
tests/test_parser.py
tests/test_source.py
tests/test_tree.py