Metadata-Version: 2.1
Name: stformatter
Version: 0.2.1
Summary: A Python formatter from formats like rst and markdown to the content tree
Home-page: https://github.com/p141592/stformatter
Author: Baryshnikov Nikolay
Author-email: mr.boiled@gmail.com
License: BSD
Platform: UNKNOWN
Classifier: License :: OSI Approved :: BSD License
